{
  "experimentId": "exp-003-raw-vs-structured",
  "variant": "structured-events",
  "metrics": {
    "accuracy": 0.925,
    "attack_type_accuracy": 1,
    "severity_accuracy": 1,
    "mitre_mapping_accuracy": 1,
    "investigation_quality": 1,
    "recommendation_quality": 0.25,
    "triage_completeness": 1,
    "analyst_utility_score": 0.79,
    "hallucination_rate": 0,
    "relevance": 0.775,
    "latency_ms": 9728,
    "latencyMs": 9728
  },
  "prediction": {
    "attackType": "Account Takeover",
    "severity": "CRITICAL",
    "summary": "A critical account takeover incident involving user sarah.chen has been detected. The incident began with an MFA bypass and an impossible travel alert, indicating a successful login from a new device in Singapore shortly after a login from London. The attacker subsequently created email forwarding rules to an external address and to delete security alerts, followed by VPN and SSH connections from the suspicious Singapore IP. The SIEM confirmed these activities as critical indicators of account compromise.",
    "timeline": [
      {
        "timestamp": "Jun 10 11:05:01",
        "event": "Successful authentication for user sarah.chen from London (203.0.113.88).",
        "source": "okta"
      },
      {
        "timestamp": "Jun 10 11:05:02",
        "event": "MFA bypass requested for user sarah.chen due to push fatigue from 203.0.113.88.",
        "source": "okta"
      },
      {
        "timestamp": "Jun 10 11:05:03",
        "event": "Successful authentication for user sarah.chen from Singapore (198.18.50.22) on a new device.",
        "source": "okta"
      },
      {
        "timestamp": "Jun 10 11:05:04",
        "event": "IMPOSSIBLE_TRAVEL alert triggered for user sarah.chen (London to Singapore in 2 minutes).",
        "source": "okta"
      },
      {
        "timestamp": "Jun 10 11:05:10",
        "event": "User sarah.chen created an inbox rule to forward all emails to attacker@dropmail.cc.",
        "source": "mail exch"
      },
      {
        "timestamp": "Jun 10 11:05:12",
        "event": "User sarah.chen created an inbox rule to delete security alerts.",
        "source": "mail exch"
      },
      {
        "timestamp": "Jun 10 11:05:15",
        "event": "User sarah.chen connected to VPN from 198.18.50.22 (first seen).",
        "source": "vpn"
      },
      {
        "timestamp": "Jun 10 11:05:18",
        "event": "SSH publickey accepted for user sarah.chen from 198.18.50.22.",
        "source": "ssh bastion"
      },
      {
        "timestamp": "Jun 10 11:05:20",
        "event": "SIEM detected account takeover indicators: impossible travel + MFA anomaly + mail forwarding.",
        "source": "siem"
      },
      {
        "timestamp": "Jun 10 11:05:21",
        "event": "CRITICAL SIEM alert for user sarah.chen, technique T1078 Valid Accounts compromise.",
        "source": "siem"
      },
      {
        "timestamp": "Jun 10 11:05:22",
        "event": "Automated response forced admin password reset for sarah.chen.",
        "source": "okta"
      },
      {
        "timestamp": "Jun 10 11:05:23",
        "event": "IDS reported session hijack risk score 92 for user sarah.chen from 198.18.50.22.",
        "source": "ids"
      }
    ],
    "recommendations": [
      "Immediately verify the identity and legitimacy of sarah.chen's recent activities and contact the user out-of-band.",
      "Investigate the MFA bypass mechanism and its root cause to prevent future occurrences and ensure MFA integrity.",
      "Perform a comprehensive forensic analysis of the compromised account and associated systems for further malicious activity, lateral movement, or data exfiltration.",
      "Block the malicious IP address (198.18.50.22) at the perimeter and review all connections originating from it.",
      "Review and remove any unauthorized inbox rules created by the compromised account and restore default settings."
    ]
  },
  "groundTruth": {
    "attackType": "Account Takeover",
    "severity": "CRITICAL",
    "mitreTechniques": [
      "T1078"
    ],
    "requiredKeywords": [
      "takeover",
      "impossible",
      "travel",
      "mfa"
    ],
    "forbiddenKeywords": [
      "brute force",
      "password spray"
    ],
    "minTimelineEvents": 4,
    "expectedRecommendationThemes": [
      "reset",
      "revoke",
      "session",
      "mfa"
    ],
    "requiredEntities": {
      "users": [
        "sarah.chen"
      ],
      "ips": [
        "198.18.50.22"
      ]
    }
  },
  "recordedAt": "2026-06-07T13:39:21.065Z",
  "fixtureId": "account_takeover",
  "scenario": "Account Takeover",
  "difficulty": "hard",
  "note": "Batch run via scripts/run-experiment.ts"
}